typed_csv/__init__.py
typed_csv/_types.py
typed_csv/typed_reader.py
typed_csv/typed_writer.py
typed_csv-0.1.2.dist-info/WHEEL
typed_csv-0.1.2.dist-info/METADATA
typed_csv-0.1.2.dist-info/RECORD
