Metadata-Version: 2.1
Name: typed-csv
Version: 0.1.2
Summary: 
Author: kesha1225
Author-email: samedov03@mail.ru
Requires-Python: >=3.7,<4.0
Classifier: Programming Language :: Python :: 3
Classifier: Programming Language :: Python :: 3.7
Classifier: Programming Language :: Python :: 3.8
Classifier: Programming Language :: Python :: 3.9
Requires-Dist: pydantic (>=1.7.2,<2.0.0)
